gaikpy/__init__.py
gaikpy/chain.py
gaikpy/chain_definitions.py
gaikpy/ga.py
gaikpy/inverse_kinematics.py
gaikpy/robot.py
gaikpy/utils.py
gaikpy/examples/__init__.py
gaikpy/examples/visualise_NICO.py
gaikpy/resources/data/nico/nico_right_20_new.p
gaikpy/resources/urdf/nico/complete_modified_bounds.urdf
gaikpy/resources/urdf/nico/meshes/Thigh_left_complete_iam_5a6ba909.STL
gaikpy/resources/urdf/nico/meshes/Thigh_right_complete_iam_6502f197.STL
gaikpy/resources/urdf/nico/meshes/finger_iam_a11b3fc1.STL
gaikpy/resources/urdf/nico/meshes/finger_segment_ipt_50d2a7f4.STL
gaikpy/resources/urdf/nico/meshes/fingertip_ipt_8417b8a9.STL
gaikpy/resources/urdf/nico/meshes/head_iam_b9cf2ea.STL
gaikpy/resources/urdf/nico/meshes/left_foot_iam_620666ef.STL
gaikpy/resources/urdf/nico/meshes/left_lower_arm_iam_5be2a521.STL
gaikpy/resources/urdf/nico/meshes/left_palm_iam_b92c61b5.STL
gaikpy/resources/urdf/nico/meshes/left_shoulder_up_iam_1ca4d925.STL
gaikpy/resources/urdf/nico/meshes/left_upper_arm_iam_49d50008.STL
gaikpy/resources/urdf/nico/meshes/left_wrist_iam_c75e4b6f.STL
gaikpy/resources/urdf/nico/meshes/neck_iam_61141f4f.STL
gaikpy/resources/urdf/nico/meshes/right_ankle_MIR_iam_c5a384f4.STL
gaikpy/resources/urdf/nico/meshes/right_ankle_iam_f4f7d16a.STL
gaikpy/resources/urdf/nico/meshes/right_foot_iam_3ff7356a.STL
gaikpy/resources/urdf/nico/meshes/right_hip_up2_MIR_iam_b8a74a0a.STL
gaikpy/resources/urdf/nico/meshes/right_hip_up2_iam_f4f7d16a.STL
gaikpy/resources/urdf/nico/meshes/right_hip_up_MIR_iam_386ac7b2.STL
gaikpy/resources/urdf/nico/meshes/right_hip_up_iam_f46f7684.STL
gaikpy/resources/urdf/nico/meshes/right_lower_arm1_iam_65a34910.STL
gaikpy/resources/urdf/nico/meshes/right_palm_iam_583b22df.STL
gaikpy/resources/urdf/nico/meshes/right_shank_MIR_iam_a2a9b5d0.STL
gaikpy/resources/urdf/nico/meshes/right_shank_iam_7a73fe91.STL
gaikpy/resources/urdf/nico/meshes/right_shoulder_up_iam_34db21c8.STL
gaikpy/resources/urdf/nico/meshes/right_upper_arm_iam_e3e9c979.STL
gaikpy-0.3.4.2.dist-info/METADATA
gaikpy-0.3.4.2.dist-info/WHEEL
gaikpy-0.3.4.2.dist-info/top_level.txt
gaikpy-0.3.4.2.dist-info/RECORD
