Metadata-Version: 2.1
Name: gaikpy
Version: 0.3.4.2
Summary: Calculates and visualises forward and (full-pose) inverse kinematic realised with a genetic algorithm (ga) for URDF models
Home-page: https://github.com/knowledgetechnologyuhh/gaikpy
Author: Erik Strahl
Author-email: strahl@informatik.uni-hamburg.de
License: UNKNOWN
Platform: Posix; Linux; MacOS X; Windows
Classifier: License :: OSI Approved :: GNU General Public License v3 (GPLv3)
Classifier: Natural Language :: English
Classifier: Programming Language :: Python
Classifier: Programming Language :: Python :: 3.6
Classifier: Programming Language :: Python :: 3.7
Classifier: Topic :: Scientific/Engineering
Requires-Dist: Sphinx
Requires-Dist: m2r2
Requires-Dist: sphinxcontrib-napoleon
Requires-Dist: numpy
Requires-Dist: scipy (==1.4.1)
Requires-Dist: sympy
Requires-Dist: math3d
Requires-Dist: matplotlib
Requires-Dist: transforms3d
Requires-Dist: urdfpy
Requires-Dist: ikpy (==3.0.1)
